Workbook

Sheet 1. Assumptions
B2: Tab 1 — ASSUMPTIONS / Giả định đầu vào
B3: Luật chơi: chỉ điền vào các ô MÀU VÀNG. Các ô khác là công thức và sẽ tự tính.
B5: 1. Product & Pricing / Sản phẩm & Giá
C6: Optimistic | D6: Base | E6: Pessimistic | F6: Đơn vị | G6: Ghi chú / Note
B7: ARPU — Giá bán bình quân/khách/tháng | C7: 199000 | D7: 149000 | E7: 129000 | F7: VND | G7: Pricing cao hơn → khó bán hơn nhưng margin tốt hơn
B8: Adoption rate — % TAM chuyển thành khách/tháng | C8: 0.008 | D8: 0.005 | E8: 0.003 | F8: %/tháng | G8: % TAM chuyển thành khách trả tiền mới mỗi tháng
B9: Total addressable market (số khách tiềm năng) | C9: 50000 | D9: 50000 | E9: 50000 | F9: khách | G9: Tổng số khách hàng tiềm năng có thể tiếp cận được
B11: 2. COGS / Chi phí biến đổi trên mỗi khách hàng
B12: API cost / khách / tháng | C12: 12000 | D12: 10000 | E12: 10000 | F12: VND | G12: Tiền gọi OpenAI/Anthropic/Gemini API
B13: Hidden costs (labeling, retraining, QA) | C13: 38000 | D13: 35000 | E13: 38000 | F13: VND | G13: Đừng quên! Đây là cục giết startup AI
B14: Infrastructure (server/cloud) / khách | C14: 8000 | D14: 6000 | E14: 7000 | F14: VND | G14: Phần allocate cloud cost cho mỗi khách
B15: → Tổng COGS / khách / tháng | C15: =C12+C13+C14 -> 58000 | D15: =D12+D13+D14 -> 51000 | E15: =E12+E13+E14 -> 55000
B17: 3. Customer Behavior / Hành vi khách hàng
B18: Monthly Churn Rate — % khách rời mỗi tháng | C18: 0.045 | D18: 0.07 | E18: 0.105 | F18: % | G18: Benchmark AI product < 5%/tháng
B19: → Số tháng ở lại trung bình | C19: =IFERROR(1/C18,0) -> 22.222222 | D19: =IFERROR(1/D18,0) -> 14.285714 | E19: =IFERROR(1/E18,0) -> 9.5238095
B21: 4. Sales & Marketing / Chi phí thu hút khách
B22: CAC — Tổng chi phí có 1 khách hàng mới | C22: 220000 | D22: 300000 | E22: 450000 | F22: VND | G22: Tổng tiền Marketing & Sales / Số khách mới
B24: 5. Fixed Costs / Chi phí cố định hàng tháng
B25: Salaries — Lương team (PM/Dev/Designer) | C25: 60000000 | D25: 50000000 | E25: 25000000 | F25: VND/tháng | G25: Pessimistic = phải hire thêm nếu khó scale
B26: Office, tools, admin | C26: 10000000 | D26: 10000000 | E26: 5000000 | F26: VND/tháng
B27: Marketing budget hàng tháng | C27: 20000000 | D27: 15000000 | E27: 5000000 | F27: VND/tháng
B28: → Tổng Fixed Cost / tháng | C28: =SUM(C25:C27) -> 90000000 | D28: =SUM(D25:D27) -> 75000000 | E28: =SUM(E25:E27) -> 35000000
B30: 6. Initial Investment / Vốn đầu tư ban đầu
B31: Vốn đầu tư ban đầu (build MVP, setup) | C31: 300000000 | D31: 300000000 | E31: 300000000 | F31: VND | G31: Chi phí 1 lần — lương team build MVP, infrastructure setup
B32: Tiền mặt ban đầu (sau khi đã trừ vốn đầu tư) | C32: 1500000000 | D32: 1200000000 | E32: 1200000000 | F32: VND | G32: Số tiền có sẵn để chi trả fixed cost trong giai đoạn đầu
B34: 7. Discount Rate / Tỷ suất chiết khấu (cho NPV)
B35: Annual discount rate (WACC) | C35: 0.2 | D35: 0.2 | E35: 0.2 | F35: %/năm | G35: Mức kỳ vọng tối thiểu của nhà đầu tư cho dự án AI rủi ro
B36: → Monthly discount rate | C36: =(1+C35)^(1/12)-1 -> 0.01530947 | D36: =(1+D35)^(1/12)-1 -> 0.01530947 | E36: =(1+E35)^(1/12)-1 -> 0.01530947
B38: 8. Decision Note / Ghi chú quyết định
B39: Finora chọn ARPU 149.000 đ/tháng dựa trên mức sẵn sàng chi trả của người trẻ thành thị cho công cụ quản lý tài chính cá nhân thông minh (tương đương 1 bữa trưa văn phòng, thấp hơn Copilot Money 13$/tháng) mang lại Gross Margin 65.8%. CAC 300.000 đ được tối ưu qua kênh phân phối kết hợp Mini-App trên ví và Referral truyền miệng, giúp CAC Payback chỉ 3.06 tháng (< 12m) và LTV/CAC đạt 4.67x (> 3.0x tiêu chuẩn vàng VC). Chi phí ẩn AI được trù bị 35.000 đ/khách (chiếm 350% API cost) cho Data Annotation, Retraining Intent Router và Human-in-the-loop QA để bảo đảm an toàn dữ liệu tài chính. Khi gặp shock thị trường (Pessimistic: Churn 10.5% [1.5x], CAC 450k [1.5x]), nhờ mô hình vận hành tinh gọn và vốn ban đầu 1.2 tỷ, Runway vẫn duy trì >= 24 tháng đảm bảo an toàn tuyệt đối.

Sheet 2. Unit Economics
B2: Tab 2 — UNIT ECONOMICS / Kinh tế đơn vị
B3: Tự động tính từ Tab 1. Kiểm tra: LTV/CAC > 3 (Base) và CAC Payback < 12 tháng.
B5: Chỉ số | C5: Optimistic | D5: Base | E5: Pessimistic | F5: Đơn vị | G5: Benchmark / Note
B7: Trên mỗi khách hàng / per customer
B8: ARPU / tháng | C8: ='1. Assumptions'!C7 -> 199000 | D8: ='1. Assumptions'!D7 -> 149000 | E8: ='1. Assumptions'!E7 -> 129000 | F8: VND | G8: Liên kết từ Tab Assumptions
B9: COGS / tháng | C9: ='1. Assumptions'!C15 -> 58000 | D9: ='1. Assumptions'!D15 -> 51000 | E9: ='1. Assumptions'!E15 -> 55000 | F9: VND
B10: → Gross Profit / tháng | C10: =C8-C9 -> 141000 | D10: =D8-D9 -> 98000 | E10: =E8-E9 -> 74000
B11: → Gross Margin % | C11: =IFERROR(C10/C8,0) -> 0.70854271 | D11: =IFERROR(D10/D8,0) -> 0.65771812 | E11: =IFERROR(E10/E8,0) -> 0.57364341 | G11: AI product target: 40-60%. SaaS truyền thống: 80%+
B13: LTV — Customer Lifetime Value
B14: Số tháng ở lại trung bình | C14: ='1. Assumptions'!C19 -> 22.222222 | D14: ='1. Assumptions'!D19 -> 14.285714 | E14: ='1. Assumptions'!E19 -> 9.5238095 | F14: tháng
B15: → LTV = Gross Profit × Số tháng ở lại | C15: =C10*C14 -> 3133333.3 | D15: =D10*D14 -> 1400000 | E15: =E10*E14 -> 704761.9 | G15: Tổng lợi nhuận gộp một khách mang lại trong vòng đời
B17: CAC — Customer Acquisition Cost
B18: CAC — Chi phí thu hút 1 khách | C18: ='1. Assumptions'!C22 -> 220000 | D18: ='1. Assumptions'!D22 -> 300000 | E18: ='1. Assumptions'!E22 -> 450000 | F18: VND
B20: Key Ratios / Tỷ lệ then chốt
B21: → LTV / CAC Ratio | C21: =IFERROR(C15/C18,0) -> 14.242424 | D21: =IFERROR(D15/D18,0) -> 4.6666667 | E21: =IFERROR(E15/E18,0) -> 1.5661376 | G21: 🎯 Target > 3.0x (tiêu chuẩn vàng VC)
B22: → CAC Payback Period | C22: =IFERROR(C18/C10,0) -> 1.5602837 | D22: =IFERROR(D18/D10,0) -> 3.0612245 | E22: =IFERROR(E18/E10,0) -> 6.0810811 | G22: 🎯 Target < 12 tháng (early-stage)
B24: Verdict / Kết luận
B25: Unit Economics Status | C25: =IF(AND(C21>=3,C22<=12),"✓ HEALTHY",IF(OR(C21<1,C22>18),"✗ UNHEALTHY","⚠ WATCH")) -> ✓ HEALTHY | D25: =IF(AND(D21>=3,D22<=12),"✓ HEALTHY",IF(OR(D21<1,D22>18),"✗ UNHEALTHY","⚠ WATCH")) -> ✓ HEALTHY | E25: =IF(AND(E21>=3,E22<=12),"✓ HEALTHY",IF(OR(E21<1,E22>18),"✗ UNHEALTHY","⚠ WATCH")) -> ⚠ WATCH

Sheet 3. P&L & ROI
B2: Tab 3 — P&L & ROI / 24 tháng
B4: Chọn scenario: | C4: Base | D4: Đổi scenario tại đây để toàn bộ P&L tự cập nhật
B6: Active scenario index: | C6: =MATCH(C4,{"Optimistic","Base","Pessimistic"},0) -> 2
B7: Selected scenario inputs ↓
B8: ARPU / khách / tháng | C8: =CHOOSE($C$6,'1. Assumptions'!C7,'1. Assumptions'!D7,'1. Assumptions'!E7) -> 149000
B9: Adoption rate | C9: =CHOOSE($C$6,'1. Assumptions'!C8,'1. Assumptions'!D8,'1. Assumptions'!E8) -> 0.005
B10: TAM (số khách tiềm năng) | C10: =CHOOSE($C$6,'1. Assumptions'!C9,'1. Assumptions'!D9,'1. Assumptions'!E9) -> 50000
B11: Total COGS / khách | C11: =CHOOSE($C$6,'1. Assumptions'!C15,'1. Assumptions'!D15,'1. Assumptions'!E15) -> 51000
B12: Monthly Churn Rate | C12: =CHOOSE($C$6,'1. Assumptions'!C18,'1. Assumptions'!D18,'1. Assumptions'!E18) -> 0.07
B13: CAC / khách mới | C13: =CHOOSE($C$6,'1. Assumptions'!C22,'1. Assumptions'!D22,'1. Assumptions'!E22) -> 300000
B14: Fixed Cost / tháng | C14: =CHOOSE($C$6,'1. Assumptions'!C28,'1. Assumptions'!D28,'1. Assumptions'!E28) -> 75000000
B15: Initial Investment | C15: =CHOOSE($C$6,'1. Assumptions'!C31,'1. Assumptions'!D31,'1. Assumptions'!E31) -> 300000000
B16: Initial Cash | C16: =CHOOSE($C$6,'1. Assumptions'!C32,'1. Assumptions'!D32,'1. Assumptions'!E32) -> 1200000000
B17: Monthly Discount Rate | C17: =CHOOSE($C$6,'1. Assumptions'!C36,'1. Assumptions'!D36,'1. Assumptions'!E36) -> 0.01530947
B20: P&L Projection — 24 months (VND)
B21: Month | C21: M1 | D21: M2 | E21: M3 | F21: M4 | G21: M5 | H21: M6 | I21: M7 | J21: M8 | K21: M9 | L21: M10 | M21: M11 | N21: M12 | O21: M13 | P21: M14 | Q21: M15 | R21: M16 | S21: M17 | T21: M18 | U21: M19 | V21: M20 | W21: M21 | X21: M22 | Y21: M23 | Z21: M24 | AA21: TOTAL
B22: New customers acquired | C22: =ROUND($C$10*$C$9,0) -> 250 | D22: =ROUND($C$10*$C$9,0) -> 250 | E22: =ROUND($C$10*$C$9,0) -> 250 | F22: =ROUND($C$10*$C$9,0) -> 250 | G22: =ROUND($C$10*$C$9,0) -> 250 | H22: =ROUND($C$10*$C$9,0) -> 250 | I22: =ROUND($C$10*$C$9,0) -> 250 | J22: =ROUND($C$10*$C$9,0) -> 250 | ... Z22: =ROUND($C$10*$C$9,0) -> 250 | AA22: =SUM(C22:Z22) -> 6000
B23: Active customers (end of month) | C23: =C22 -> 250 | D23: =C23*(1-$C$12)+D22 -> 482.5 | E23: =D23*(1-$C$12)+E22 -> 698.725 | F23: =E23*(1-$C$12)+F22 -> 899.81425 | G23: =F23*(1-$C$12)+G22 -> 1086.8273 | H23: =G23*(1-$C$12)+H22 -> 1260.7493 | I23: =H23*(1-$C$12)+I22 -> 1422.4969 | J23: =I23*(1-$C$12)+J22 -> 1572.9221 | K23: =J23*(1-$C$12)+K22 -> 1712.8176 | ... Z23: =Y23*(1-$C$12)+Z22 -> 2945.6326
B25: Revenue | C25: =C23*$C$8 -> 37250000 | D25: =D23*$C$8 -> 71892500 | E25: =E23*$C$8 -> 1.0411002e+08 | F25: =F23*$C$8 -> 1.3407232e+08 | G25: =G23*$C$8 -> 1.6193726e+08 | H25: =H23*$C$8 -> 1.8785165e+08 | I25: =I23*$C$8 -> 2.1195204e+08 | J25: =J23*$C$8 -> 2.3436539e+08 | ... Z25: =Z23*$C$8 -> 4.3889926e+08 | AA25: =SUM(C25:Z25) -> 6.9403384e+09
B26: COGS (variable cost) | C26: =C23*$C$11 -> 12750000 | D26: =D23*$C$11 -> 24607500 | E26: =E23*$C$11 -> 35634975 | F26: =F23*$C$11 -> 45890527 | G26: =G23*$C$11 -> 55428190 | H26: =H23*$C$11 -> 64298217 | I26: =I23*$C$11 -> 72547341 | J26: =J23*$C$11 -> 80219028 | ... Z26: =Z23*$C$11 -> 1.5022726e+08 | AA26: =SUM(C26:Z26) -> 2.3755521e+09
B27: Gross Profit | C27: =C25-C26 -> 24500000 | D27: =D25-D26 -> 47285000 | E27: =E25-E26 -> 68475050 | F27: =F25-F26 -> 88181796 | G27: =G25-G26 -> 1.0650907e+08 | H27: =H25-H26 -> 1.2355344e+08 | I27: =I25-I26 -> 1.394047e+08 | J27: =J25-J26 -> 1.5414637e+08 | ... Z27: =Z25-Z26 -> 2.88672e+08 | AA27: =SUM(C27:Z27) -> 4.5647863e+09
B28: Marketing/Acquisition cost | C28: =C22*$C$13 -> 75000000 | D28: =D22*$C$13 -> 75000000 | E28: =E22*$C$13 -> 75000000 | F28: =F22*$C$13 -> 75000000 | G28: =G22*$C$13 -> 75000000 | H28: =H22*$C$13 -> 75000000 | I28: =I22*$C$13 -> 75000000 | J28: =J22*$C$13 -> 75000000 | ... Z28: =Z22*$C$13 -> 75000000 | AA28: =SUM(C28:Z28) -> 1800000000
B29: Fixed cost (salaries + ops) | C29: =$C$14 -> 75000000 | D29: =$C$14 -> 75000000 | E29: =$C$14 -> 75000000 | F29: =$C$14 -> 75000000 | G29: =$C$14 -> 75000000 | H29: =$C$14 -> 75000000 | I29: =$C$14 -> 75000000 | J29: =$C$14 -> 75000000 | ... Z29: =$C$14 -> 75000000 | AA29: =SUM(C29:Z29) -> 1800000000
B30: Operating Profit (EBITDA) | C30: =C27-C28-C29 -> -125500000 | D30: =D27-D28-D29 -> -102715000 | E30: =E27-E28-E29 -> -81524950 | F30: =F27-F28-F29 -> -61818204 | G30: =G27-G28-G29 -> -43490929 | H30: =H27-H28-H29 -> -26446564 | I30: =I27-I28-I29 -> -10595305 | J30: =J27-J28-J29 -> 4146366.6 | ... Z30: =Z27-Z28-Z29 -> 1.38672e+08 | AA30: =SUM(C30:Z30) -> 9.647863e+08
B32: Cash Flow (after investment) | C32: =C30-$C$15 -> -425500000 | D32: =D30 -> -102715000 | E32: =E30 -> -81524950 | F32: =F30 -> -61818204 | G32: =G30 -> -43490929 | H32: =H30 -> -26446564 | I32: =I30 -> -10595305 | J32: =J30 -> 4146366.6 | K32: =K30 -> 17856121 | ... Z32: =Z30 -> 1.38672e+08 | AA32: =SUM(C32:Z32) -> 6.647863e+08
B33: Cash Position (cumulative) | C33: =$C$16+C32 -> 774500000 | D33: =C33+D32 -> 671785000 | E33: =D33+E32 -> 590260050 | F33: =E33+F32 -> 5.2844185e+08 | G33: =F33+G32 -> 4.8495092e+08 | H33: =G33+H32 -> 4.5850435e+08 | I33: =H33+I32 -> 4.4790905e+08 | J33: =I33+J32 -> 4.5205541e+08 | K33: =J33+K32 -> 4.6991154e+08 | ... Z33: =Y33+Z32 -> 1.8647863e+09
B36: ROI Metrics / Chỉ số đánh giá tổng thể dự án
B37: NPV (Net Present Value, mil VND) | C37: =(NPV($C$17,D32:Z32)+C32)/1000000 -> 350.28696 | D37: ="(target: > 0)" -> (target: > 0)
B38: IRR (Annual) | C38: =IFERROR((1+IRR(C32:Z32))^12-1,0) -> 0.60828843 | D38: ="(target: > "&TEXT(CHOOSE($C$6,'1. Assumptions'!C35,'1. Assumptions'!D35,'1. Assumptions'!E35),"0.0%")&")" -> (target: > 20.0%)
B39: Project Payback (months) | C39: =IFERROR(MATCH(TRUE(),INDEX(C41:Z41>=0,0),0),"> 24") -> 19 | D39: ="(target: < 24)" -> (target: < 24)
B40: Runway (months until cash = 0) | C40: =IFERROR(MATCH(TRUE(),INDEX(C33:Z33<0,0),0)-1,">= 24") -> >= 24 | D40: ="(target: >= 12)" -> (target: >= 12)
B41: (helper: cumulative cash flow) | C41: =C32 -> -425500000 | D41: =C41+D32 -> -528215000 | E41: =D41+E32 -> -609739950 | F41: =E41+F32 -> -6.7155815e+08 | G41: =F41+G32 -> -7.1504908e+08 | H41: =G41+H32 -> -7.4149565e+08 | I41: =H41+I32 -> -7.5209095e+08 | J41: =I41+J32 -> -7.4794459e+08 | K41: =J41+K32 -> -7.3008846e+08 | ... Z41: =Y41+Z32 -> 6.647863e+08
B43: Final Verdict / Có nên làm dự án này?
B44: Project Decision | C44: =IF(AND(C37>0,C38>CHOOSE($C$6,'1. Assumptions'!C35,'1. Assumptions'!D35,'1. Assumptions'!E35)),"✓ GO — NPV+ và IRR > WACC",IF(C37<0,"✗ NO-GO — NPV âm: dự án không tạo giá trị","⚠ HOLD — IRR thấp hơn kỳ vọng, cần điều chỉnh")) -> ✓ GO — NPV+ và IRR > WACC
